noimport.py
noimport-0.0.1.dist-info/LICENSE
noimport-0.0.1.dist-info/METADATA
noimport-0.0.1.dist-info/WHEEL
noimport-0.0.1.dist-info/top_level.txt
noimport-0.0.1.dist-info/RECORD
