Metadata-Version: 2.1
Name: noimport
Version: 0.0.1
Summary: A simple package to prevent the abusive use of 'import' statement in Python.
Home-page: https://github.com/AndyKhang404/noimport
Author: Andy Khang
Author-email: andykhang404@gmail.com
License: MIT
Keywords: no import noimport suicide
Platform: UNKNOWN
Classifier: Development Status :: 5 - Production/Stable
Classifier: Intended Audience :: Developers
Classifier: Programming Language :: Python :: 3 :: Only
Classifier: Programming Language :: Python :: 3.4
Classifier: Programming Language :: Python :: 3.5
Classifier: Programming Language :: Python :: 3.6
Classifier: Programming Language :: Python :: 3.7
Classifier: Programming Language :: Python :: 3.8
Classifier: Programming Language :: Python :: 3.9
Classifier: Topic :: Utilities
Classifier: License :: OSI Approved :: MIT License
Classifier: Operating System :: OS Independent
Requires-Python: >=3.4
